snakeplane/__init__.py
snakeplane/constants.py
snakeplane/helper_classes.py
snakeplane/interface_utilities.py
snakeplane/plugin_factory.py
snakeplane/plugin_utilities.py
snakeplane/version.py
SnakePlane-1.0.0a23.dist-info/LICENSE
SnakePlane-1.0.0a23.dist-info/METADATA
SnakePlane-1.0.0a23.dist-info/WHEEL
SnakePlane-1.0.0a23.dist-info/top_level.txt
SnakePlane-1.0.0a23.dist-info/RECORD
