Metadata-Version: 2.1
Name: SnakePlane
Version: 1.0.0a23
Summary: The Alteryx Python SDK Abstraction Layer
Home-page: https://github.com/alteryx/snakeplane
Author: Alteryx
Author-email: awalden@alteryx.com
License: Apache License 2.0
Platform: UNKNOWN
Requires-Python: >=3.6.0
Requires-Dist: numpy (==1.19.1)
Requires-Dist: xmltodict (==0.11.0)
